jira_field_sync/__init__.py
jira_field_sync/updater.py
jira_field_sync-0.2.0.dist-info/LICENSE
jira_field_sync-0.2.0.dist-info/METADATA
jira_field_sync-0.2.0.dist-info/WHEEL
jira_field_sync-0.2.0.dist-info/entry_points.txt
jira_field_sync-0.2.0.dist-info/top_level.txt
jira_field_sync-0.2.0.dist-info/RECORD
