Metadata-Version: 2.1
Name: jira-field-sync
Version: 0.2.0
Summary: A tool to manage default configurations for Jira projects.
Author-email: Salih Ergüt <salih.ergut@oredata.com>
License: MIT
Classifier: Programming Language :: Python :: 3
Classifier: License :: OSI Approved :: MIT License
Classifier: Operating System :: OS Independent
License-File: LICENSE
Requires-Dist: PyYAML>=5.4
Requires-Dist: requests>=2.25
